README.txt
setup.cfg
setup.py
pvz/__init__.py
pvz/core.py
pvz/extra.py
pvz.egg-info/PKG-INFO
pvz.egg-info/SOURCES.txt
pvz.egg-info/dependency_links.txt
pvz.egg-info/top_level.txt